{
  "all":
  [
    {"class": "Math 31A", "term": ["Fall", "Winter", "Spring"], "major": "Required", "category": "Math", "abbrev": "31A"},
    {"class": "Math 31B", "term": ["Fall", "Winter", "Spring"], "major": "Required", "category": "Math", "abbrev": "31B"},
    {"class": "Math 32A", "term": ["Fall", "Winter", "Spring"], "major": "Required", "category": "Math", "abbrev": "32A"},
    {"class": "Math 32B", "term": ["Fall", "Winter", "Spring"], "major": "Required", "category": "Math", "abbrev": "32B"},
    {"class": "Math 33A", "term": ["Fall", "Winter", "Spring"], "major": "Required", "category": "Math", "abbrev": "33A"},
    {"class": "Math 170A", "term": "Fall", "major": "Varies", "category": "Math", "abbrev": "170A"},
    {"class": "Stats 10", "term": ["Fall", "Winter", "Spring"], "major": "Required", "category": "Lower", "abbrev": "10"},
    {"class": "Stats 20", "term": ["Fall", "Winter", "Spring"], "major": "Required", "category": "Lower", "abbrev": "20"},
    {"class": "Stats 100A", "term": ["Fall", "Winter", "Spring"], "major": "Required", "category": "100", "abbrev": "A"},
    {"class": "Stats 100B", "term": ["Fall", "Winter", "Spring"], "major": "Required", "category": "100", "abbrev": "B"},
    {"class": "Stats 100C", "term": ["Fall", "Spring"], "major": "Required", "category": "100", "abbrev": "C"},
    {"class": "Stats 101A", "term": "Fall", "major": "Varies", "category": "101", "abbrev": "A"},
    {"class": "Stats 101B", "term": "Winter", "major": "Varies", "category": "101", "abbrev": "B"},
    {"class": "Stats 101C", "term": "Spring", "major": "Varies", "category": "101", "abbrev": "C"},
    {"class": "Stats 102A", "term": "Fall", "major": "Varies", "category": "102", "abbrev": "A"},
    {"class": "Stats 102B", "term": "Winter", "major": "Varies", "category": "102", "abbrev": "B"},
    {"class": "Stats 102C", "term": "Spring", "major": "Varies", "category": "102", "abbrev": "C"},
    {"class": "Stats 130", "term": ["Fall", "Spring"], "major": "Varies", "category": "Elective", "abbrev": "130"},
    {"class": "Stats C155", "term": "Winter", "major": "Elective", "category": "Elective", "abbrev": "C155"},
    {"class": "Stats C161", "term": "Spring", "major": "Elective", "category": "Elective", "abbrev": "C161"},
    {"class": "Stats 170", "term": "Spring", "major": "Elective", "category": "Elective", "abbrev": "170"},
    {"class": "Stats C180", "term": "Winter", "major": "Elective", "category": "Elective", "abbrev": "C180"},
    {"class": "Stats 140SL", "term": ["Fall", "Winter"], "major": "Required", "category": "Consulting", "abbrev": "140SL"},
    {"class": "Stats 141SL", "term": ["Winter", "Spring"], "major": "Required", "category": "Consulting", "abbrev": "141SL"}
  ]
}
